lucidium/__args__.py
lucidium/__init__.py
lucidium/__main__.py
lucidium/_version_.py
lucidium/agents/__base__.py
lucidium/agents/__init__.py
lucidium/agents/commands/__init__.py
lucidium/agents/commands/registry.py
lucidium/agents/commands/play/__args__.py
lucidium/agents/commands/play/__init__.py
lucidium/agents/commands/play/__main__.py
lucidium/agents/components/__init__.py
lucidium/agents/components/q_table.py
lucidium/agents/nlm/__args__.py
lucidium/agents/nlm/__base__.py
lucidium/agents/nlm/__init__.py
lucidium/agents/nlm/__util__.py
lucidium/agents/nlm/layers/__init__.py
lucidium/agents/nlm/layers/expansion.py
lucidium/agents/nlm/layers/inference.py
lucidium/agents/nlm/layers/linear.py
lucidium/agents/nlm/layers/logic.py
lucidium/agents/nlm/layers/mlp.py
lucidium/agents/nlm/layers/permutation.py
lucidium/agents/nlm/layers/reduction.py
lucidium/agents/q_learning/__args__.py
lucidium/agents/q_learning/__base__.py
lucidium/agents/q_learning/__init__.py
lucidium/agents/q_learning/__main__.py
lucidium/agents/sarsa/__args__.py
lucidium/agents/sarsa/__base__.py
lucidium/agents/sarsa/__init__.py
lucidium/agents/sarsa/__main__.py
lucidium/environments/__base__.py
lucidium/environments/__init__.py
lucidium/environments/block_world/__args__.py
lucidium/environments/block_world/__base__.py
lucidium/environments/block_world/__init__.py
lucidium/environments/block_world/components/__init__.py
lucidium/environments/block_world/components/block.py
lucidium/environments/block_world/components/world.py
lucidium/environments/grid_world/__args__.py
lucidium/environments/grid_world/__base__.py
lucidium/environments/grid_world/__init__.py
lucidium/environments/grid_world/__main__.py
lucidium/environments/grid_world/actions.py
lucidium/environments/grid_world/components/__init__.py
lucidium/environments/grid_world/components/grid.py
lucidium/environments/grid_world/components/squares/__base__.py
lucidium/environments/grid_world/components/squares/__init__.py
lucidium-0.2.0.dist-info/METADATA
lucidium-0.2.0.dist-info/WHEEL
lucidium-0.2.0.dist-info/entry_points.txt
lucidium-0.2.0.dist-info/top_level.txt
lucidium-0.2.0.dist-info/RECORD
